synthetig/__init__.py
synthetig/data/__init__.py
synthetig/data/demo_data.py
synthetig/models/__init__.py
synthetig/models/CTGAN/__init__.py
synthetig/models/CTGAN/conditional.py
synthetig/models/CTGAN/data.py
synthetig/models/CTGAN/model.py
synthetig/models/CTGAN/models.py
synthetig/models/CTGAN/sampler.py
synthetig/models/CTGAN/transformer.py
synthetig-0.0.2a1.dist-info/LICENSE
synthetig-0.0.2a1.dist-info/METADATA
synthetig-0.0.2a1.dist-info/WHEEL
synthetig-0.0.2a1.dist-info/top_level.txt
synthetig-0.0.2a1.dist-info/RECORD
