Metadata-Version: 2.1
Name: synthetig
Version: 0.0.2a1
Summary: Synthetig: An open-source synthetic data generation platform.
Home-page: https://github.com/synthetig/synthetig
Author: Jonathan Hind and Nick Lee-McMaster
Author-email: info@synthetig.ai
License: UNKNOWN
Platform: UNKNOWN
Classifier: Programming Language :: Python :: 3.7
Classifier: License :: OSI Approved :: Apache Software License
Classifier: Operating System :: OS Independent
Requires-Dist: torch (==1.6.0)
Requires-Dist: scikit-learn (==0.23.2)
Requires-Dist: numpy (==1.19)
Requires-Dist: pandas (==1.1.3)
